inaccel/gzip/__init__.py
inaccel/gzip/_gzip.py
inaccel/zlib/__init__.py
inaccel/zlib/_zlib.py
inaccel_gzip_zlib-3.11.0.2.dist-info/LICENSE
inaccel_gzip_zlib-3.11.0.2.dist-info/METADATA
inaccel_gzip_zlib-3.11.0.2.dist-info/NOTICE
inaccel_gzip_zlib-3.11.0.2.dist-info/WHEEL
inaccel_gzip_zlib-3.11.0.2.dist-info/top_level.txt
inaccel_gzip_zlib-3.11.0.2.dist-info/zip-safe
inaccel_gzip_zlib-3.11.0.2.dist-info/RECORD
